toolmockers.py
toolmockers-1.0.0.dist-info/METADATA
toolmockers-1.0.0.dist-info/WHEEL
toolmockers-1.0.0.dist-info/licenses/LICENSE
toolmockers-1.0.0.dist-info/RECORD
