Metadata-Version: 2.4
Name: toolmockers
Version: 1.0.0
Summary: LLM-powered mocking library for generating realistic mock responses in AI agent tools
Project-URL: Homepage, https://github.com/sgorblex/toolmockers
Project-URL: Documentation, https://github.com/sgorblex/toolmockers#readme
Project-URL: Repository, https://github.com/sgorblex/toolmockers.git
Project-URL: Issues, https://github.com/sgorblex/toolmockers/issues
Project-URL: Changelog, https://github.com/sgorblex/toolmockers/releases
Author-email: Alessandro Clerici Lorenzini <foss@aclerici.me>
Maintainer-email: Alessandro Clerici Lorenzini <foss@aclerici.me>
License-Expression: MIT
License-File: LICENSE
Keywords: agents,ai,development,langchain,llm,mock,testing,tools
Classifier: Development Status :: 4 - Beta
Classifier: Intended Audience :: Developers
Classifier: License :: OSI Approved :: MIT License
Classifier: Operating System :: OS Independent
Classifier: Programming Language :: Python :: 3
Classifier: Programming Language :: Python :: 3.9
Classifier: Programming Language :: Python :: 3.10
Classifier: Programming Language :: Python :: 3.11
Classifier: Programming Language :: Python :: 3.12
Classifier: Programming Language :: Python :: 3.13
Classifier: Topic :: Software Development :: Libraries :: Python Modules
Classifier: Topic :: Software Development :: Testing
Classifier: Topic :: Software Development :: Testing :: Mocking
Classifier: Typing :: Typed
Requires-Python: >=3.9
Requires-Dist: langchain-core>=0.3.0
Provides-Extra: dev
Requires-Dist: black>=22.0.0; extra == 'dev'
Requires-Dist: isort>=5.0.0; extra == 'dev'
Provides-Extra: examples
Requires-Dist: langchain-openai>=0.1.0; extra == 'examples'
